tugboat/__init__.py
tugboat/build.py
tugboat/cli.py
tugboat/config.py
tugboat/construct.py
tugboat/run.py
tugboat/utils.py
tugboat/validators.py
tugboat_cli-0.0.6.dist-info/METADATA
tugboat_cli-0.0.6.dist-info/WHEEL
tugboat_cli-0.0.6.dist-info/entry_points.txt
tugboat_cli-0.0.6.dist-info/top_level.txt
tugboat_cli-0.0.6.dist-info/RECORD
