Metadata-Version: 2.1
Name: tugboat-cli
Version: 0.0.6
Summary: Generate and interact with a Docker image created from a local directory.
Author-email: Daniel Molitor <molitdj97@gmail.com>
Project-URL: Homepage, https://github.com/dmolitor/tugboat
Requires-Python: >=3.8
Requires-Dist: click >=8.0.0
Requires-Dist: prompt-toolkit >=3.0.0
Requires-Dist: PyYAML
